{"tiger": {"global_account": {"portfolio": {"quantity": {"UPRO": 30, "SOXL": 6, "U": 40}, "average_cost": {"UPRO": 66.4, "SOXL": 296.38, "U": 70.18}, "latest_price": {"UPRO": 80.94, "SOXL": 570.5, "U": 151.5}, "rate": {"UPRO": 0.22, "SOXL": 0.92, "U": 1.16}, "latest_time": {"UPRO": null, "SOXL": null, "U": null}, "market_value": {"UPRO": 2428.2, "SOXL": 3423.0, "U": 6060.0}}, "market_value": 11908.23, "net_value": 11958.48, "updated": "2021-01-14 09:05:03", "cash": 50.25}, "standard_account": {"portfolio": {"quantity": {}, "average_cost": {}, "latest_price": {}, "rate": {}, "market_value": {}, "latest_time": {}}, "market_value": 0.0, "net_value": 94.69, "updated": "2020-11-26 08:37:11", "cash": 94.69}, "simulation_account": {"portfolio": {"quantity": {"AAPL": 160, "ABBV": 120, "ABT": 115, "ACN": 82, "AMD": 122, "AMGN": 40, "AMT": 45, "AVGO": 31, "BAC": 421, "C": 183, "CHAU": 506, "CHTR": 22, "CQQQ": 189, "DHR": 55, "FAS": 219, "GE": 1180, "GS": 98, "GSK": 261, "HON": 64, "IBM": 85, "INTC": 203, "JNJ": 69, "LMT": 27, "MDT": 103, "MRK": 124, "MS": 191, "NVDA": 22, "NVS": 114, "SNY": 233, "SOXL": 34, "SPXU": 1134, "SPY": 32, "T": 330, "TECL": 40, "TQQQ": 80, "TSM": 203, "UPRO": 368, "WFC": 379, "YINN": 560}, "average_cost": {"AAPL": 119.08, "ABBV": 94.95, "ABT": 92.12, "ACN": 234.23, "AMD": 81.38, "AMGN": 233.44, "AMT": 220.95, "AVGO": 315.89, "BAC": 23.71, "C": 53.25, "CHAU": 19.74, "CHTR": 455.53, "CQQQ": 52.78, "DHR": 177.04, "FAS": 38.19, "GE": 7.64, "GS": 203.24, "GSK": 38.29, "HON": 155.26, "IBM": 120.15, "INTC": 49.21, "JNJ": 143.02, "LMT": 372.72, "MDT": 102.59, "MRK": 80.26, "MS": 52.26, "NVDA": 569.93, "NVS": 84.96, "SNY": 42.89, "SOXL": 295.85, "SPXU": 8.8, "SPY": 310.76, "T": 30.23, "TECL": 336.73, "TQQQ": 139.91, "TSM": 49.28, "UPRO": 63.05, "WFC": 26.32, "YINN": 16.6}, "latest_price": {"AAPL": 131.28, "ABBV": 112.45, "ABT": 112.55, "ACN": 257.12, "AMD": 92.2, "AMGN": 237.98, "AMT": 216.7, "AVGO": 451.21, "BAC": 33.55, "C": 67.0, "CHAU": 48.87, "CHTR": 618.01, "CQQQ": 88.6, "DHR": 245.0, "FAS": 72.25, "GE": 11.6, "GS": 303.2, "GSK": 37.68, "HON": 206.51, "IBM": 127.15, "INTC": 57.0, "JNJ": 159.8, "LMT": 346.74, "MDT": 118.72, "MRK": 82.38, "MS": 75.75, "NVDA": 542.9, "NVS": 95.97, "SNY": 48.04, "SOXL": 570.5, "SPXU": 5.58, "SPY": 380.7, "T": 28.63, "TECL": 400.79, "TQQQ": 185.85, "TSM": 120.05, "UPRO": 80.94, "WFC": 33.89, "YINN": 22.78}, "rate": {"AAPL": 0.1, "ABBV": 0.18, "ABT": 0.22, "ACN": 0.1, "AMD": 0.13, "AMGN": 0.02, "AMT": -0.02, "AVGO": 0.43, "BAC": 0.42, "C": 0.26, "CHAU": 1.48, "CHTR": 0.36, "CQQQ": 0.68, "DHR": 0.38, "FAS": 0.89, "GE": 0.52, "GS": 0.49, "GSK": -0.02, "HON": 0.33, "IBM": 0.06, "INTC": 0.16, "JNJ": 0.12, "LMT": -0.07, "MDT": 0.16, "MRK": 0.03, "MS": 0.45, "NVDA": -0.05, "NVS": 0.13, "SNY": 0.12, "SOXL": 0.93, "SPXU": -0.37, "SPY": 0.23, "T": -0.05, "TECL": 0.19, "TQQQ": 0.33, "TSM": 1.44, "UPRO": 0.28, "WFC": 0.29, "YINN": 0.37}, "latest_time": {"AAPL": null, "ABBV": null, "ABT": null, "ACN": null, "AMD": null, "AMGN": null, "AMT": null, "AVGO": null, "BAC": null, "C": null, "CHAU": null, "CHTR": null, "CQQQ": null, "DHR": null, "FAS": null, "GE": null, "GS": null, "GSK": null, "HON": null, "IBM": null, "INTC": null, "JNJ": null, "LMT": null, "MDT": null, "MRK": null, "MS": null, "NVDA": null, "NVS": null, "SNY": null, "SOXL": null, "SPXU": null, "SPY": null, "T": null, "TECL": null, "TQQQ": null, "TSM": null, "UPRO": null, "WFC": null, "YINN": null}, "market_value": {"AAPL": 21004.8, "ABBV": 13494.0, "ABT": 12943.25, "ACN": 21083.73, "AMD": 11248.4, "AMGN": 9519.35, "AMT": 9751.5, "AVGO": 13987.51, "BAC": 14124.55, "C": 12261.0, "CHAU": 24728.22, "CHTR": 13596.22, "CQQQ": 16745.4, "DHR": 13475.0, "FAS": 15822.75, "GE": 13688.0, "GS": 29713.6, "GSK": 9834.48, "HON": 13216.64, "IBM": 10807.75, "INTC": 11571.0, "JNJ": 11026.2, "LMT": 9361.98, "MDT": 12228.16, "MRK": 10215.12, "MS": 14468.25, "NVDA": 11943.8, "NVS": 10940.58, "SNY": 11193.32, "SOXL": 19397.0, "SPXU": 6327.72, "SPY": 12182.4, "T": 9447.9, "TECL": 16031.6, "TQQQ": 14868.0, "TSM": 24370.15, "UPRO": 29785.92, "WFC": 12844.31, "YINN": 12756.8}}, "market_value": 562006.36, "net_value": 1260529.6412, "updated": "2021-01-14 09:05:04", "cash": 698523.28}}, "futu": {"REAL": {"portfolio": {"quantity": {"US.WFC": 75.0, "US.UPRO": 30.0, "US.TECL": 6.0, "US.NVS": 23.0, "US.NVDA": 3.0, "US.IBM": 16.0, "US.GLD": 17.0, "US.C": 37.0, "US.AMGN": 1.0, "US.AMD": 22.0, "US.ADBE": 4.0}, "average_cost": {"US.WFC": 26.32, "US.UPRO": 66.31, "US.TECL": 340.0, "US.NVS": 86.02, "US.NVDA": 536.49, "US.IBM": 120.12, "US.GLD": 174.9, "US.C": 53.24, "US.AMGN": 233.43, "US.AMD": 88.08, "US.ADBE": 495.36}, "latest_price": {"US.WFC": 33.89, "US.UPRO": 80.96, "US.TECL": 401.0, "US.NVS": 95.2, "US.NVDA": 542.9, "US.IBM": 127.15, "US.GLD": 173.36, "US.C": 67.04, "US.AMGN": 237.74, "US.AMD": 92.19, "US.ADBE": 474.0}, "rate": {"US.WFC": 0.29, "US.UPRO": 0.22, "US.TECL": 0.18, "US.NVS": 0.11, "US.NVDA": 0.01, "US.IBM": 0.06, "US.GLD": -0.01, "US.C": 0.26, "US.AMGN": 0.02, "US.AMD": 0.05, "US.ADBE": -0.04}, "market_value": {"US.WFC": 2541.75, "US.UPRO": 2428.8, "US.TECL": 2406.0, "US.NVS": 2189.6, "US.NVDA": 1628.7, "US.IBM": 2034.4, "US.GLD": 2947.12, "US.C": 2480.48, "US.AMGN": 237.74, "US.AMD": 2028.18, "US.ADBE": 1896.0}, "latest_time": {"US.WFC": null, "US.UPRO": null, "US.TECL": null, "US.NVS": null, "US.NVDA": null, "US.IBM": null, "US.GLD": null, "US.C": null, "US.AMGN": null, "US.AMD": null, "US.ADBE": null}}, "market_value": 22818.77, "net_value": 23005.6, "updated": "2021-01-14 09:05:04", "cash": 186.83}, "SIMULATE": {"portfolio": {"quantity": {"US.YINN": 437.0}, "average_cost": {"US.YINN": 22.81}, "latest_price": {"US.YINN": 22.81}, "rate": {"US.YINN": -0.0}, "market_value": {"US.YINN": 9967.97}, "latest_time": {"US.YINN": null}}, "market_value": 9967.97, "net_value": 99994.45, "updated": "2021-01-14 09:05:04", "cash": 90026.48}}}