{"tiger": {"global_account": {"portfolio": {"quantity": {"AAPL": 31, "BILI": 25, "U": 19}, "average_cost": {"AAPL": 134.1, "BILI": 127.28, "U": 108.01}, "latest_price": {"AAPL": 137.11, "BILI": 121.17, "U": 105.7}, "rate": {"AAPL": 0.02, "BILI": -0.05, "U": -0.02}, "latest_time": {"AAPL": null, "BILI": null, "U": null}, "market_value": {"AAPL": 4250.41, "BILI": 3029.25, "U": 2008.3}}, "market_value": 9296.7, "net_value": 9306.14, "updated": "2021-07-02 08:05:03", "cash": 9.44}, "standard_account": {"portfolio": {"quantity": {}, "average_cost": {}, "latest_price": {}, "rate": {}, "market_value": {}, "latest_time": {}}, "market_value": 0.0, "net_value": 94.69, "updated": "2020-11-26 08:37:11", "cash": 94.69}, "simulation_account": {"portfolio": {"quantity": {"AAPL": 160, "ABBV": 120, "ABT": 115, "ACN": 82, "ADBE": 15, "AMGN": 36, "AMT": 45, "AVGO": 31, "BA": 44, "BAC": 421, "C": 178, "CHTR": 22, "DHR": 53, "FAS": 185, "FB": 37, "GE": 1180, "GS": 98, "GSK": 259, "IBM": 85, "INTC": 203, "JNJ": 69, "LABD": 539, "LMT": 27, "MDT": 103, "MRK": 131, "MS": 191, "NFLX": 29, "NVDA": 19, "NVS": 114, "PFE": 300, "SNY": 233, "SOXS": 404, "SPXU": 226, "SPY": 32, "T": 330, "TSM": 211, "UPRO": 368, "WFC": 379}, "average_cost": {"AAPL": 119.08, "ABBV": 94.95, "ABT": 92.12, "ACN": 234.23, "ADBE": 493.57, "AMGN": 252.6, "AMT": 220.95, "AVGO": 315.89, "BA": 210.66, "BAC": 23.71, "C": 62.3, "CHTR": 455.53, "DHR": 222.97, "FAS": 68.11, "FB": 273.1, "GE": 7.64, "GS": 203.24, "GSK": 35.6, "IBM": 120.15, "INTC": 49.21, "JNJ": 143.02, "LABD": 15.99, "LMT": 372.72, "MDT": 102.59, "MRK": 76.31, "MS": 52.26, "NFLX": 547.14, "NVDA": 575.66, "NVS": 84.96, "PFE": 36.65, "SNY": 42.89, "SOXS": 15.78, "SPXU": 44.02, "SPY": 310.76, "T": 30.23, "TSM": 118.12, "UPRO": 63.05, "WFC": 26.32}, "latest_price": {"AAPL": 137.11, "ABBV": 114.1, "ABT": 117.16, "ACN": 300.0, "ADBE": 584.73, "AMGN": 246.9, "AMT": 271.79, "AVGO": 469.5, "BA": 239.52, "BAC": 41.55, "C": 71.1, "CHTR": 721.36, "DHR": 271.9, "FAS": 112.15, "FB": 354.05, "GE": 13.47, "GS": 375.19, "GSK": 40.18, "IBM": 146.66, "INTC": 56.0, "JNJ": 166.0, "LABD": 18.05, "LMT": 380.22, "MDT": 126.24, "MRK": 78.1, "MS": 91.95, "NFLX": 533.54, "NVDA": 806.48, "NVS": 91.65, "PFE": 39.52, "SNY": 52.56, "SOXS": 7.39, "SPXU": 17.92, "SPY": 430.38, "T": 29.12, "TSM": 118.42, "UPRO": 115.25, "WFC": 45.4}, "rate": {"AAPL": 0.15, "ABBV": 0.2, "ABT": 0.27, "ACN": 0.28, "ADBE": 0.18, "AMGN": -0.02, "AMT": 0.23, "AVGO": 0.49, "BA": 0.14, "BAC": 0.75, "C": 0.14, "CHTR": 0.58, "DHR": 0.22, "FAS": 0.65, "FB": 0.3, "GE": 0.76, "GS": 0.85, "GSK": 0.13, "IBM": 0.22, "INTC": 0.14, "JNJ": 0.16, "LABD": 0.13, "LMT": 0.02, "MDT": 0.23, "MRK": 0.02, "MS": 0.76, "NFLX": -0.02, "NVDA": 0.4, "NVS": 0.08, "PFE": 0.08, "SNY": 0.23, "SOXS": -0.53, "SPXU": -0.59, "SPY": 0.38, "T": -0.04, "TSM": 0.0, "UPRO": 0.83, "WFC": 0.73}, "latest_time": {"AAPL": null, "ABBV": null, "ABT": null, "ACN": null, "ADBE": null, "AMGN": null, "AMT": null, "AVGO": null, "BA": null, "BAC": null, "C": null, "CHTR": null, "DHR": null, "FAS": null, "FB": null, "GE": null, "GS": null, "GSK": null, "IBM": null, "INTC": null, "JNJ": null, "LABD": null, "LMT": null, "MDT": null, "MRK": null, "MS": null, "NFLX": null, "NVDA": null, "NVS": null, "PFE": null, "SNY": null, "SOXS": null, "SPXU": null, "SPY": null, "T": null, "TSM": null, "UPRO": null, "WFC": null}, "market_value": {"AAPL": 21937.6, "ABBV": 13692.0, "ABT": 13473.4, "ACN": 24600.0, "ADBE": 8770.95, "AMGN": 8888.4, "AMT": 12230.55, "AVGO": 14554.5, "BA": 10538.88, "BAC": 17492.55, "C": 12655.8, "CHTR": 15869.92, "DHR": 14410.7, "FAS": 20747.75, "FB": 13099.85, "GE": 15894.6, "GS": 36768.62, "GSK": 10406.62, "IBM": 12466.1, "INTC": 11368.0, "JNJ": 11454.0, "LABD": 9728.95, "LMT": 10265.94, "MDT": 13002.72, "MRK": 10231.09, "MS": 17562.45, "NFLX": 15472.66, "NVDA": 15323.12, "NVS": 10448.1, "PFE": 11856.03, "SNY": 12246.48, "SOXS": 2985.56, "SPXU": 4049.92, "SPY": 13772.16, "T": 9609.6, "TSM": 24986.62, "UPRO": 42412.0, "WFC": 17206.6}}, "market_value": 562480.79, "net_value": 1300125.4769, "updated": "2021-07-02 08:05:02", "cash": 737644.69}}, "futu": {"REAL": {"portfolio": {"quantity": {"US.TQQQ": 20.0, "US.SOXL": 55.0, "US.MRK": 26.0, "US.LABU": 27.0, "US.FAS": 18.0, "US.EL": 6.0, "US.CQQQ": 15.0}, "average_cost": {"US.TQQQ": 102.51, "US.SOXL": 36.75, "US.MRK": 77.85, "US.LABU": 72.96, "US.FAS": 112.1, "US.EL": 316.4, "US.CQQQ": 85.0}, "latest_price": {"US.TQQQ": 122.25, "US.SOXL": 42.6, "US.MRK": 77.99, "US.LABU": 78.64, "US.FAS": 112.15, "US.EL": 317.0, "US.CQQQ": 82.98}, "rate": {"US.TQQQ": 0.19, "US.SOXL": 0.16, "US.MRK": 0.0, "US.LABU": 0.08, "US.FAS": 0.0, "US.EL": 0.0, "US.CQQQ": -0.02}, "market_value": {"US.TQQQ": 2445.0, "US.SOXL": 2343.0, "US.MRK": 2027.74, "US.LABU": 2123.28, "US.FAS": 2018.7, "US.EL": 1902.0, "US.CQQQ": 1244.69}, "latest_time": {"US.TQQQ": null, "US.SOXL": null, "US.MRK": null, "US.LABU": null, "US.FAS": null, "US.EL": null, "US.CQQQ": null}}, "market_value": 14104.411, "net_value": 25536.921, "updated": "2021-07-02 08:05:03", "cash": 11432.51}, "SIMULATE": {"portfolio": {"quantity": {"US.FB": 36.0, "US.SOXS": 630.0, "US.LMT": 29.0, "US.GSK": 280.0, "US.DHR": 44.0, "US.NFLX": 19.0, "US.NVS": 115.0, "US.PFE": 272.0, "US.TSM": 84.0, "US.ADBE": 20.0}, "average_cost": {"US.FB": 273.01, "US.SOXS": 15.75, "US.LMT": 332.21, "US.GSK": 35.06, "US.DHR": 222.52, "US.NFLX": 523.39, "US.NVS": 86.47, "US.PFE": 36.24, "US.TSM": 117.7, "US.ADBE": 493.39}, "latest_price": {"US.FB": 354.39, "US.SOXS": 7.39, "US.LMT": 380.22, "US.GSK": 40.17, "US.DHR": 272.21, "US.NFLX": 533.54, "US.NVS": 91.65, "US.PFE": 39.56, "US.TSM": 118.42, "US.ADBE": 584.73}, "rate": {"US.FB": 0.3, "US.SOXS": -0.53, "US.LMT": 0.14, "US.GSK": 0.15, "US.DHR": 0.22, "US.NFLX": 0.02, "US.NVS": 0.06, "US.PFE": 0.09, "US.TSM": 0.01, "US.ADBE": 0.19}, "market_value": {"US.FB": 12758.04, "US.SOXS": 4655.7, "US.LMT": 11026.38, "US.GSK": 11247.6, "US.DHR": 11977.24, "US.NFLX": 10137.26, "US.NVS": 10539.75, "US.PFE": 10760.32, "US.TSM": 9947.28, "US.ADBE": 11694.6}, "latest_time": {"US.FB": null, "US.SOXS": null, "US.LMT": null, "US.GSK": null, "US.DHR": null, "US.NFLX": null, "US.NVS": null, "US.PFE": null, "US.TSM": null, "US.ADBE": null}}, "market_value": 104744.17, "net_value": 106897.15, "updated": "2021-07-02 08:05:03", "cash": 2152.98}}}