{"tiger": {"global_account": {"portfolio": {"quantity": {}, "average_cost": {}, "latest_price": {}, "rate": {}, "rate_inday": {}, "market_value": {}, "latest_time": {}, "support": {}, "resistant": {}}, "market_value": 0.0, "net_value": 2134.7, "updated": "2025-02-21 09:05:01", "cash": 2134.7}, "standard_account": {"portfolio": {"quantity": {}, "average_cost": {}, "latest_price": {}, "rate": {}, "market_value": {}, "latest_time": {}, "support": {}, "resistant": {}}, "market_value": 0, "net_value": 94.69, "updated": "2020-11-26 08:37:11", "cash": 94.69}, "simulation_account": {"portfolio": {"quantity": {"AAPL": 160, "ABBV": 120, "ABT": 115, "ACN": 82, "ADBE": 15, "AMGN": 36, "AMT": 45, "AVGO": 31, "BA": 44, "BAC": 421, "C": 178, "CHTR": 22, "DHR": 53, "FAS": 185, "FB": 37, "GE": 147, "GS": 98, "GSK": 259, "IBM": 85, "INTC": 203, "JNJ": 69, "LABD": 539, "LMT": 27, "MDT": 103, "MRK": 131, "MS": 191, "NFLX": 29, "NVDA": 76, "NVS": 114, "PFE": 300, "SNY": 233, "SOXS": 404, "SPXU": 226, "SPY": 32, "T": 330, "TSM": 211, "UPRO": 368, "WFC": 379}, "average_cost": {"AAPL": 119.08, "ABBV": 94.95, "ABT": 92.12, "ACN": 234.23, "ADBE": 493.57, "AMGN": 252.6, "AMT": 220.95, "AVGO": 315.89, "BA": 210.66, "BAC": 23.71, "C": 62.3, "CHTR": 455.53, "DHR": 222.97, "FAS": 68.11, "FB": 273.1, "GE": 61.1, "GS": 203.24, "GSK": 35.6, "IBM": 120.15, "INTC": 49.21, "JNJ": 143.02, "LABD": 15.99, "LMT": 372.72, "MDT": 102.59, "MRK": 76.31, "MS": 52.26, "NFLX": 547.14, "NVDA": 143.91, "NVS": 84.96, "PFE": 36.65, "SNY": 42.89, "SOXS": 15.78, "SPXU": 44.02, "SPY": 310.76, "T": 30.23, "TSM": 118.12, "UPRO": 63.05, "WFC": 26.32}, "latest_price": {"AAPL": 245.83, "ABBV": 164.4, "ABT": 112.01, "ACN": 337.05, "ADBE": 536.87, "AMGN": 334.64, "AMT": 278.45, "AVGO": 235.8, "BA": 201.88, "BAC": 39.87, "C": 83.94, "CHTR": 339.14, "DHR": 272.92, "FAS": 176.76, "FB": 170.16, "GE": 208.36, "GS": 668.15, "GSK": 39.64, "IBM": 263.3, "INTC": 26.09, "JNJ": 167.57, "LABD": 19.03, "LMT": 436.29, "MDT": 86.66, "MRK": 117.23, "MS": 140.69, "NFLX": 1043.33, "NVDA": 140.11, "NVS": 106.98, "PFE": 28.58, "SNY": 51.76, "SOXS": 6.28, "SPXU": 15.95, "SPY": 544.76, "T": 21.84, "TSM": 208.74, "UPRO": 98.02, "WFC": 55.11}, "rate": {"AAPL": 0.28, "ABBV": 0.27, "ABT": 0.37, "ACN": 0.44, "ADBE": 0.35, "AMGN": -0.11, "AMT": 0.32, "AVGO": 0.58, "BA": 0.04, "BAC": 0.76, "C": 0.16, "CHTR": 0.79, "DHR": 0.45, "FAS": 0.83, "FB": 0.39, "GE": 0.73, "GS": 1.04, "GSK": 0.15, "IBM": 0.17, "INTC": 0.1, "JNJ": 0.21, "LABD": 0.17, "LMT": -0.03, "MDT": 0.3, "MRK": 0, "MS": 1, "NFLX": 0.04, "NVDA": 0.56, "NVS": 0.09, "PFE": 0.26, "SNY": 0.21, "SOXS": -0.6, "SPXU": -0.65, "SPY": 0.46, "T": -0.09, "TSM": 0.01, "UPRO": 1.11, "WFC": 0.74}, "latest_time": {"AAPL": null, "ABBV": null, "ABT": null, "ACN": null, "ADBE": null, "AMGN": null, "AMT": null, "AVGO": null, "BA": null, "BAC": null, "C": null, "CHTR": null, "DHR": null, "FAS": null, "FB": null, "GE": null, "GS": null, "GSK": null, "IBM": null, "INTC": null, "JNJ": null, "LABD": null, "LMT": null, "MDT": null, "MRK": null, "MS": null, "NFLX": null, "NVDA": null, "NVS": null, "PFE": null, "SNY": null, "SOXS": null, "SPXU": null, "SPY": null, "T": null, "TSM": null, "UPRO": null, "WFC": null}, "market_value": {"AAPL": 24305.6, "ABBV": 14491.21, "ABT": 14532.55, "ACN": 27594.47, "ADBE": 9969.75, "AMGN": 8121.96, "AMT": 13162.5, "AVGO": 15469, "BA": 9678.24, "BAC": 17610.43, "C": 12826.68, "CHTR": 17966.52, "DHR": 17178.89, "FAS": 23045.45, "FB": 14037.06, "GE": 15529.08, "GS": 40561.22, "GSK": 10567.2, "IBM": 11955.25, "INTC": 10972.15, "JNJ": 11948.04, "LABD": 10079.3, "LMT": 9713.38, "MDT": 13723.72, "MRK": 10012.33, "MS": 19970.96, "NFLX": 16516.08, "NVDA": 17020.2, "NVS": 10532.46, "PFE": 13830, "SNY": 12064.74, "SOXS": 2553.28, "SPXU": 3451, "SPY": 14478.08, "T": 9048.6, "TSM": 25111.11, "UPRO": 48859.36, "WFC": 17305.14}, "support": {"AAPL": null, "ABBV": 163, "ABT": 111.41, "ACN": 332.55, "ADBE": null, "AMGN": 328.28, "AMT": 238.27, "AVGO": 230.87, "BA": 200.57, "BAC": null, "C": null, "CHTR": 336.42, "DHR": 271.67, "FAS": null, "FB": null, "GE": 205.2, "GS": null, "GSK": 37.74, "IBM": null, "INTC": null, "JNJ": null, "LABD": null, "LMT": null, "MDT": 84.6, "MRK": 117.14, "MS": 138.73, "NFLX": 1031.42, "NVDA": 137.67, "NVS": null, "PFE": null, "SNY": 50.57, "SOXS": null, "SPXU": null, "SPY": 542.35, "T": 21.69, "TSM": 204.99, "UPRO": 97.29, "WFC": 54.95}, "resistant": {"AAPL": null, "ABBV": null, "ABT": null, "ACN": 341.66, "ADBE": 540.27, "AMGN": null, "AMT": null, "AVGO": null, "BA": 222.34, "BAC": null, "C": null, "CHTR": null, "DHR": null, "FAS": null, "FB": 192.9, "GE": null, "GS": null, "GSK": null, "IBM": null, "INTC": null, "JNJ": 176.55, "LABD": null, "LMT": 440.82, "MDT": null, "MRK": 119.68, "MS": null, "NFLX": null, "NVDA": null, "NVS": null, "PFE": 29.28, "SNY": null, "SOXS": null, "SPXU": null, "SPY": 548.98, "T": null, "TSM": null, "UPRO": null, "WFC": null}}, "market_value": 595792.99, "net_value": 1335309.92656, "updated": "2021-09-01 08:05:03", "cash": 739516.93}}, "futu": {"REAL": {"portfolio": {"quantity": {}, "average_cost": {}, "latest_price": {}, "rate": {}, "rate_inday": {}, "market_value": {}, "latest_time": {}, "support": {}, "resistant": {}}, "market_value": 0.0, "net_value": 24029.8755, "updated": "2025-02-21 09:05:01", "cash": 4000.07}, "SIMULATE": {"portfolio": {"quantity": {"LABU": 21.0, "YINN": 71.0, "CHAU": 130.0, "TNA": 37.0, "SOXL": 69.0, "UYM": 71.0, "UCO": 76.0, "BOIL": 46.0, "UGL": 21.0, "DRN": 169.0, "EDC": 63.0, "UVXY": 89.0, "UTSL": 55.0, "EURL": 91.0, "UUP": 67.0, "FAS": 12.0, "UPRO": 21.0, "TECL": 21.0, "UDOW": 19.0, "RETL": 219.0, "TQQQ": 27.0, "DUSL": 31.0, "ERX": 32.0}, "average_cost": {"LABU": 93.09, "YINN": 27.65, "CHAU": 15.17, "TNA": 53.51, "SOXL": 28.52, "UYM": 28.18, "UCO": 26.26, "BOIL": 43.4, "UGL": 94.85, "DRN": 11.78, "EDC": 31.18, "UVXY": 22.43, "UTSL": 35.33, "EURL": 21.69, "UUP": 29.53, "FAS": 165.31, "UPRO": 92.48, "TECL": 94.56, "UDOW": 104.18, "RETL": 9.09, "TQQQ": 72.32, "DUSL": 61.09, "ERX": 60.71}, "latest_price": {"LABU": 94.6, "YINN": 43.15, "CHAU": 15.09, "TNA": 42.73, "SOXL": 31.7, "UYM": 25.64, "UCO": 28.76, "BOIL": 88.73, "UGL": 114.69, "DRN": 10.97, "EDC": 34.9, "UVXY": 17.55, "UTSL": 37.0, "EURL": 27.0, "UUP": 28.98, "FAS": 176.76, "UPRO": 98.02, "TECL": 97.55, "UDOW": 104.25, "RETL": 8.98, "TQQQ": 89.3, "DUSL": 61.44, "ERX": 64.45}, "rate": {"LABU": 0.02, "YINN": 0.56, "CHAU": -0.01, "TNA": -0.2, "SOXL": 0.11, "UYM": -0.09, "UCO": 0.1, "BOIL": 1.04, "UGL": 0.21, "DRN": -0.07, "EDC": 0.12, "UVXY": -0.22, "UTSL": 0.05, "EURL": 0.24, "UUP": -0.02, "FAS": 0.07, "UPRO": 0.06, "TECL": 0.03, "UDOW": 0.0, "RETL": -0.01, "TQQQ": 0.23, "DUSL": 0.01, "ERX": 0.06}, "rate_inday": {"LABU": 0, "YINN": 0, "CHAU": 0, "TNA": 0, "SOXL": 0, "UYM": 0, "UCO": 0, "BOIL": 0, "UGL": 0, "DRN": 0, "EDC": 0, "UVXY": 0, "UTSL": 0, "EURL": 0, "UUP": 0, "FAS": 0, "UPRO": 0, "TECL": 0, "UDOW": 0, "RETL": 0, "TQQQ": 0, "DUSL": 0, "ERX": 0}, "market_value": {"LABU": 1986.6, "YINN": 3063.65, "CHAU": 1961.7, "TNA": 1581.01, "SOXL": 2187.3, "UYM": 1820.75, "UCO": 2185.76, "BOIL": 4081.58, "UGL": 2408.49, "DRN": 1853.93, "EDC": 2198.7, "UVXY": 1561.95, "UTSL": 2035.0, "EURL": 2456.7, "UUP": 1941.66, "FAS": 2121.12, "UPRO": 2058.42, "TECL": 2048.55, "UDOW": 1980.75, "RETL": 1966.62, "TQQQ": 2411.1, "DUSL": 1904.64, "ERX": 2062.4}, "latest_time": {"LABU": null, "YINN": null, "CHAU": null, "TNA": null, "SOXL": null, "UYM": null, "UCO": null, "BOIL": null, "UGL": null, "DRN": null, "EDC": null, "UVXY": null, "UTSL": null, "EURL": null, "UUP": null, "FAS": null, "UPRO": null, "TECL": null, "UDOW": null, "RETL": null, "TQQQ": null, "DUSL": null, "ERX": null}, "support": {"LABU": null, "YINN": null, "CHAU": null, "TNA": null, "SOXL": null, "UYM": null, "UCO": null, "BOIL": null, "UGL": null, "DRN": null, "EDC": null, "UVXY": null, "UTSL": null, "EURL": null, "UUP": null, "FAS": null, "UPRO": null, "TECL": null, "UDOW": null, "RETL": null, "TQQQ": null, "DUSL": null, "ERX": null}, "resistant": {"LABU": null, "YINN": null, "CHAU": null, "TNA": null, "SOXL": null, "UYM": null, "UCO": null, "BOIL": null, "UGL": null, "DRN": null, "EDC": null, "UVXY": null, "UTSL": null, "EURL": null, "UUP": null, "FAS": null, "UPRO": null, "TECL": null, "UDOW": null, "RETL": null, "TQQQ": null, "DUSL": null, "ERX": null}}, "market_value": 49878.375, "net_value": 135000.397, "updated": "2025-02-21 09:05:01", "cash": 85122.023}}, "pingan": {"snowball": {"portfolio": {"quantity": {}, "average_cost": {}, "latest_price": {}, "rate": {}, "latest_time": {}, "market_value": {}, "support": {}, "resistant": {}}, "market_value": 0, "net_value": 1.37, "updated": "2025-02-21 07:17:58", "cash": 1.37}}}